{
  "$schema": "https://turbo.build/schema.json",
  "globalEnv": [
    "DATABASE_URL",
    "PORT",
    "FRONTEND_ORIGIN",
    "MULTICA_SERVER_URL",
    "DOCS_URL",
    "COMPOSE_PROJECT_NAME",
    "POSTGRES_DB",
    "POSTGRES_PORT",
    "DESKTOP_RENDERER_PORT",
    "DESKTOP_APP_SUFFIX"
  ],
  "tasks": {
    "build": {
      "dependsOn": ["^build"],
      "inputs": ["src/**", "app/**", "**/*.ts", "**/*.tsx", "**/*.css"],
      "outputs": [".next/**", "!.next/cache/**", "dist/**", "out/**"]
    },
    "dev": {
      "cache": false,
      "persistent": true
    },
    "dev:staging": {
      "cache": false,
      "persistent": true
    },
    "typecheck": {
      "dependsOn": ["^typecheck"]
    },
    "test": {
      "dependsOn": ["^typecheck"]
    },
    "lint": {
      "dependsOn": ["^typecheck"]
    }
  }
}
